{
  "@largeMonitorVeryRelaxedGridWidth": "$container-large-monitor-very-relaxed-grid-width",
  "@largeMonitorRelaxedGridWidth": "$container-large-monitor-relaxed-grid-width",
  "@computerVeryRelaxedGridWidth": "$container-computer-very-relaxed-grid-width",
  "@tabletVeryRelaxedGridWidth": "$container-tablet-very-relaxed-grid-width",
  "@mobileVeryRelaxedGridWidth": "$container-mobile-very-relaxed-grid-width",
  "@veryRelaxedGridGutterWidth": "$container-very-relaxed-grid-gutter-width",
  "@largeMonitorMinimumGutter": "$container-large-monitor-minimum-gutter",
  "@computerRelaxedGridWidth": "$container-computer-relaxed-grid-width",
  "@mobileRelaxedGridWidth": "$container-mobile-relaxed-grid-width",
  "@relaxedGridGutterWidth": "$container-relaxed-grid-gutter-width",
  "@tabletRelaxedGridWidth": "$container-tablet-relaxed-grid-width",
  "@largeMonitorGridWidth": "$container-large-monitor-grid-width",
  "@computerMinimumGutter": "$container-computer-minimum-gutter",
  "@mobileMinimumGutter": "$container-mobile-minimum-gutter",
  "@tabletMinimumGutter": "$container-tablet-minimum-gutter",
  "@largeMonitorGutter": "$container-large-monitor-gutter",
  "@computerGridWidth": "$container-computer-grid-width",
  "@largeMonitorWidth": "$container-large-monitor-width",
  "@mobileGridWidth": "$container-mobile-grid-width",
  "@tabletGridWidth": "$container-tablet-grid-width",
  "@gridGutterWidth": "$container-grid-gutter-width",
  "@textFontFamily": "$container-text-font-family",
  "@textLineHeight": "$container-text-line-height",
  "@computerGutter": "$container-computer-gutter",
  "@computerWidth": "$container-computer-width",
  "@tabletGutter": "$container-tablet-gutter",
  "@mobileGutter": "$container-mobile-gutter",
  "@mobileWidth": "$container-mobile-width",
  "@tabletWidth": "$container-tablet-width",
  "@textWidth": "$container-text-width",
  "@maxWidth": "$container-max-width",
  "@textSize": "$container-text-size"
}